metallic_charts/__init__.py
metallic_charts/charts/__init__.py
metallic_charts/charts/bars.py
metallic_charts/charts/base.py
metallic_charts/charts/pie.py
metallic_charts/charts/planar.py
metallic_charts/main.py
metallic_charts/utils/__init__.py
metallic_charts/utils/filtering.py
metallic_charts/utils/rounding.py
metallic_charts-0.0.1.dist-info/METADATA
metallic_charts-0.0.1.dist-info/WHEEL
metallic_charts-0.0.1.dist-info/RECORD
